{
  "blockers": [],
  "context": {
    "command": "versioning reentry update",
    "gitInfo": {
      "author": "edcalderon",
      "branch": "develop",
      "commit": "bed71db",
      "timestamp": "2026-06-29T15:19:21-05:00"
    },
    "trigger": "auto",
    "versioningInfo": {
      "newVersion": "1.0.294"
    }
  },
  "currentPhase": "building",
  "dependencies": [],
  "lastUpdated": "2026-06-30T20:16:56.101Z",
  "milestone": {
    "id": "wallet-system",
    "title": "Alternun Wallet System (non-custodial, multi-chain)"
  },
  "milestones": [],
  "nextSteps": [
    {
      "description": "Fixed mi-perfil.tsx tab-switching bug: ?tab= URL sync effect had 'tabs' in its deps array, but tabs is recreated every render (useAppTranslation's t() isn't memoized) — caused the active tab to snap back to the URL param on every re-render. Fixed by depending only on params.tab, and added router.setParams() to keep the URL in sync when switching tabs via UI. Affects all profile tabs (ranking/wallet/perfil), not wallet-specific. Ready for 1.1.0 release.",
      "id": "next",
      "priority": 1
    }
  ],
  "risks": [],
  "roadmapFile": ".versioning/ROADMAP.md",
  "schemaVersion": "1.1",
  "syncMetadata": {
    "lastSuccessfulSync": "1970-01-01T00:00:00.000Z",
    "lastSyncAttempt": "1970-01-01T00:00:00.000Z"
  },
  "updatedBy": "edcalderon",
  "version": "1.0.294",
  "versioning": {
    "currentVersion": "1.0.294",
    "previousVersion": "1.0.42",
    "versionType": "patch"
  }
}
