{
  "blockers": [],
  "context": {
    "command": "versioning bump",
    "gitInfo": {
      "author": "edcalderon",
      "branch": "develop",
      "commit": "b61b205",
      "timestamp": "2026-04-07T09:53:12-05:00"
    },
    "options": {
      "commit": true,
      "config": "versioning.config.json",
      "tag": true
    },
    "trigger": "postVersion",
    "versioningInfo": {
      "newVersion": "1.0.40",
      "versionType": "patch"
    }
  },
  "currentPhase": "staging",
  "dependencies": [],
  "lastUpdated": "2026-04-07T14:53:26.357Z",
  "milestone": null,
  "milestones": [],
  "nextSteps": [
    {
      "description": "Verify deployment and update documentation",
      "id": "next",
      "priority": 1
    }
  ],
  "risks": [],
  "roadmapFile": ".versioning/ROADMAP.md",
  "schemaVersion": "1.1",
  "syncMetadata": {
    "lastSuccessfulSync": "1970-01-01T00:00:00.000Z",
    "lastSyncAttempt": "1970-01-01T00:00:00.000Z"
  },
  "updatedBy": "unknown",
  "version": "1.0.40",
  "versioning": {
    "currentVersion": "1.0.40",
    "previousVersion": "0.0.0",
    "versionType": "patch"
  }
}
